{
  "editor:save-file": [],
  "obsidian-git:push": [
    {
      "modifiers": [
        "Mod"
      ],
      "key": "S"
    }
  ],
  "editor:open-search-replace": [
    {
      "modifiers": [
        "Mod"
      ],
      "key": "F"
    }
  ],
  "editor:open-search": [],
  "editor:toggle-highlight": [
    {
      "modifiers": [
        "Mod"
      ],
      "key": "H"
    }
  ],
  "editor:toggle-code": [
    {
      "modifiers": [
        "Mod",
        "Shift"
      ],
      "key": "C"
    }
  ],
  "obsidian-git:pull": [
    {
      "modifiers": [
        "Mod"
      ],
      "key": "P"
    }
  ],
  "command-palette:open": []
}